super_scad_chess/Bishop.py
super_scad_chess/King.py
super_scad_chess/Knight.py
super_scad_chess/Pawn.py
super_scad_chess/Queen.py
super_scad_chess/Rook.py
super_scad_chess/__init__.py
super_scad_chess/include/bishop_profile.dxf
super_scad_chess/include/bishop_profile.svg
super_scad_chess/include/cross_profile.svg
super_scad_chess/include/horse3.stl
super_scad_chess/include/king_profile.svg
super_scad_chess/include/knight_profile.svg
super_scad_chess/include/pawn_profile.svg
super_scad_chess/include/queen_crown2.stl
super_scad_chess/include/queen_profile.svg
super_scad_chess/include/rook_profile.svg
super_scad_chess-0.1.0.dist-info/LICENSE
super_scad_chess-0.1.0.dist-info/METADATA
super_scad_chess-0.1.0.dist-info/WHEEL
super_scad_chess-0.1.0.dist-info/RECORD
